odoo/addons/invader_payment_adyen_klarna_sale/README.rst
odoo/addons/invader_payment_adyen_klarna_sale/__init__.py
odoo/addons/invader_payment_adyen_klarna_sale/__manifest__.py
odoo/addons/invader_payment_adyen_klarna_sale/i18n/invader_payment_adyen_klarna_sale.pot
odoo/addons/invader_payment_adyen_klarna_sale/models/__init__.py
odoo/addons/invader_payment_adyen_klarna_sale/models/sale_order.py
odoo/addons/invader_payment_adyen_klarna_sale/readme/CONFIGURE.rst
odoo/addons/invader_payment_adyen_klarna_sale/readme/CONTRIBUTORS.rst
odoo/addons/invader_payment_adyen_klarna_sale/readme/DESCRIPTION.rst
odoo/addons/invader_payment_adyen_klarna_sale/readme/HISTORY.rst
odoo/addons/invader_payment_adyen_klarna_sale/static/description/index.html
odoo14_addon_invader_payment_adyen_klarna_sale-14.0.1.0.3.dist-info/METADATA
odoo14_addon_invader_payment_adyen_klarna_sale-14.0.1.0.3.dist-info/WHEEL
odoo14_addon_invader_payment_adyen_klarna_sale-14.0.1.0.3.dist-info/top_level.txt
odoo14_addon_invader_payment_adyen_klarna_sale-14.0.1.0.3.dist-info/RECORD
